instack_undercloud/__init__.py
instack_undercloud/undercloud.py
instack_undercloud/validator.py
instack_undercloud/tests/__init__.py
instack_undercloud/tests/test_undercloud.py
instack_undercloud/tests/test_validator.py
instack_undercloud-9.5.1.data/data/share/instack-undercloud/undercloud.conf.sample
instack_undercloud-9.5.1.data/data/share/instack-undercloud/centos-cr/README.rst
instack_undercloud-9.5.1.data/data/share/instack-undercloud/centos-cr/pre-install.d/00-enable-cr-repo
instack_undercloud-9.5.1.data/data/share/instack-undercloud/instack-vm/README.md
instack_undercloud-9.5.1.data/data/share/instack-undercloud/instack-vm/element-deps
instack_undercloud-9.5.1.data/data/share/instack-undercloud/instack-vm/package-installs.yaml
instack_undercloud-9.5.1.data/data/share/instack-undercloud/instack-vm/extra-data.d/50-add-instack-files
instack_undercloud-9.5.1.data/data/share/instack-undercloud/instack-vm/install.d/50-ip-forward
instack_undercloud-9.5.1.data/data/share/instack-undercloud/instack-vm/install.d/51-instack-files
instack_undercloud-9.5.1.data/data/share/instack-undercloud/instack-vm/post-install.d/90-remove-cloud-init
instack_undercloud-9.5.1.data/data/share/instack-undercloud/instack-vm/post-install.d/90-set-hostname
instack_undercloud-9.5.1.data/data/share/instack-undercloud/json-files/centos-7-undercloud-packages.json
instack_undercloud-9.5.1.data/data/share/instack-undercloud/json-files/rhel-7-undercloud-packages.json
instack_undercloud-9.5.1.data/data/share/instack-undercloud/overcloud-full/README.rst
instack_undercloud-9.5.1.data/data/share/instack-undercloud/overcloud-full/package-installs.yaml
instack_undercloud-9.5.1.data/data/share/instack-undercloud/overcloud-full/install.d/50-persistent-journal
instack_undercloud-9.5.1.data/data/share/instack-undercloud/overcloud-full/post-install.d/50-remove-libvirt-default-net
instack_undercloud-9.5.1.data/data/share/instack-undercloud/pip-and-virtualenv-override/README.md
instack_undercloud-9.5.1.dist-info/AUTHORS
instack_undercloud-9.5.1.dist-info/LICENSE
instack_undercloud-9.5.1.dist-info/METADATA
instack_undercloud-9.5.1.dist-info/WHEEL
instack_undercloud-9.5.1.dist-info/entry_points.txt
instack_undercloud-9.5.1.dist-info/pbr.json
instack_undercloud-9.5.1.dist-info/top_level.txt
instack_undercloud-9.5.1.dist-info/RECORD
