Metadata-Version: 2.1
Name: instack-undercloud
Version: 9.5.1
Summary: instack-undercloud
Home-page: https://git.openstack.org/cgit/openstack/instack-undercloud
Author: OpenStack
Author-email: openstack-dev@lists.openstack.org
License: UNKNOWN
Platform: UNKNOWN
Classifier: Environment :: OpenStack
Classifier: Intended Audience :: Information Technology
Classifier: Intended Audience :: System Administrators
Classifier: License :: OSI Approved :: Apache Software License
Classifier: Operating System :: POSIX :: Linux
Classifier: Programming Language :: Python
Classifier: Programming Language :: Python :: 2
Classifier: Programming Language :: Python :: 2.7
Classifier: Programming Language :: Python :: 3
Classifier: Programming Language :: Python :: 3.5
Requires-Dist: six (>=1.10.0)
Requires-Dist: python-ironicclient (>=2.3.0)
Requires-Dist: python-keystoneclient (>=3.8.0)
Requires-Dist: python-novaclient (>=9.1.0)
Requires-Dist: python-mistralclient (!=3.2.0,>=3.1.0)
Requires-Dist: python-swiftclient (>=3.2.0)
Requires-Dist: oslo.config (>=5.2.0)
Requires-Dist: oslo.utils (>=3.33.0)
Requires-Dist: psutil (>=3.2.2)
Requires-Dist: netaddr (>=0.7.18)
Requires-Dist: netifaces (>=0.10.4)
Requires-Dist: pystache (>=0.5.4)
Requires-Dist: os-refresh-config (>=6.0.0)
Requires-Dist: os-apply-config (>=5.0.0)
Requires-Dist: os-client-config (>=1.28.0)
Requires-Dist: openstacksdk (>=0.17.2)
